jina_ai_mcp_server/__init__.py
jina_ai_mcp_server/client.py
jina_ai_mcp_server/main.py
jina_ai_mcp_server/server.py
jina_ai_mcp_server/tools/__init__.py
jina_ai_mcp_server/tools/classifier_image.py
jina_ai_mcp_server/tools/classifier_text.py
jina_ai_mcp_server/tools/deepsearch.py
jina_ai_mcp_server/tools/embeddings.py
jina_ai_mcp_server/tools/reader.py
jina_ai_mcp_server/tools/reranker.py
jina_ai_mcp_server/tools/search.py
jina_ai_mcp_server/tools/segmenter.py
jina_ai_mcp_server-0.2.0.dist-info/licenses/LICENSE
jina_ai_mcp_server-0.2.0.dist-info/METADATA
jina_ai_mcp_server-0.2.0.dist-info/WHEEL
jina_ai_mcp_server-0.2.0.dist-info/entry_points.txt
jina_ai_mcp_server-0.2.0.dist-info/top_level.txt
jina_ai_mcp_server-0.2.0.dist-info/RECORD
