Metadata-Version: 2.4
Name: jina-ai-mcp-server
Version: 0.2.0
Summary: MCP Server for Jina AI APIs
Author-email: Jina AI <dev@jina.ai>
License: Apache-2.0
Project-URL: Homepage, https://github.com/jina-ai/jina-ai-mcp-server
Project-URL: Repository, https://github.com/jina-ai/jina-ai-mcp-server.git
Project-URL: Bug Tracker, https://github.com/jina-ai/jina-ai-mcp-server/issues
Keywords: jina-ai,mcp,ai,tools,llm,agent
Classifier: Development Status :: 4 - Beta
Classifier: Intended Audience :: Developers
Classifier: License :: OSI Approved :: Apache Software License
Classifier: Programming Language :: Python :: 3.10
Classifier: Programming Language :: Python :: 3.11
Classifier: Programming Language :: Python :: 3.12
Classifier: Topic :: Scientific/Engineering :: Artificial Intelligence
Classifier: Typing :: Typed
Requires-Python: >=3.8
License-File: LICENSE
Requires-Dist: requests
Requires-Dist: mcp.py
Dynamic: license-file
